prim/__init__.py
prim/__main__.py
prim/collocation.py
prim/example.py
prim/hybrid.py
prim/spliced_pn.py
prim/taylort3.py
prim/waveform.py
prim/waveform_generator.py
gw_prim-0.2.5.dist-info/LICENSE
gw_prim-0.2.5.dist-info/METADATA
gw_prim-0.2.5.dist-info/WHEEL
gw_prim-0.2.5.dist-info/entry_points.txt
gw_prim-0.2.5.dist-info/RECORD
