Metadata-Version: 2.1
Name: gw-prim
Version: 0.2.5
Summary: 
Author: Sebastian Khan
Author-email: KhanS22@cardiff.ac.uk
Requires-Python: >=3.10,<4.0
Classifier: Programming Language :: Python :: 3
Classifier: Programming Language :: Python :: 3.10
Classifier: Programming Language :: Python :: 3.11
Classifier: Programming Language :: Python :: 3.12
Requires-Dist: gw-phenom (>=1.0.1,<2.0.0)
Requires-Dist: h5py (>=3.11.0,<4.0.0)
Requires-Dist: lalsuite (>=7.23,<8.0)
Requires-Dist: lmfit (>=1.3.2,<2.0.0)
Requires-Dist: numpy (==1.26.4)
Requires-Dist: scipy (>=1.14.1,<2.0.0)
Requires-Dist: sympy (>=1.13.2,<2.0.0)
